README.md
setup.py
scrapgo/__init__.py
scrapgo.egg-info/PKG-INFO
scrapgo.egg-info/SOURCES.txt
scrapgo.egg-info/dependency_links.txt
scrapgo.egg-info/requires.txt
scrapgo.egg-info/top_level.txt
scrapgo/core/__init__.py
scrapgo/core/http/__init__.py
scrapgo/core/http/browser/__init__.py
scrapgo/core/http/browser/browser_requests.py
scrapgo/core/http/browser/driver/__init__.py
scrapgo/core/http/browser/driver/base.py
scrapgo/core/http/browser/driver/utils.py
scrapgo/core/http/request/__init__.py
scrapgo/core/http/request/base.py
scrapgo/core/http/request/cached_requests.py
scrapgo/core/http/request/exceptions.py
scrapgo/core/http/request/file_requests.py
scrapgo/core/http/request/utils.py
scrapgo/core/parser/__init__.py
scrapgo/core/parser/exceptions.py
scrapgo/core/parser/soup.py
scrapgo/crawler/__init__.py
scrapgo/crawler/base.py
scrapgo/crawler/meta.py
scrapgo/crawler/actions/__init__.py
scrapgo/crawler/actions/base.py
scrapgo/crawler/actions/exceptions.py
scrapgo/crawler/actions/reducer.py
scrapgo/crawler/actions/utils.py
scrapgo/lib/__init__.py
scrapgo/lib/curl.py
scrapgo/lib/etc.py
scrapgo/lib/exceptions.py
scrapgo/lib/logger.py
scrapgo/lib/module.py
scrapgo/lib/plural.py
scrapgo/lib/regex.py
scrapgo/lib/sh.py
scrapgo/lib/times.py
scrapgo/lib/url.py
scrapgo/lib/parser/__init__.py
scrapgo/lib/parser/date.py
scrapgo/lib/parser/html.py
scrapgo/lib/parser/js.py
scrapgo/lib/parser/text.py
scrapgo/pipeline/__init__.py
scrapgo/pipeline/excel.py
scrapgo/pipeline/file.py
scrapgo/pipeline/jsonl.py
scrapgo/settings/__init__.py
scrapgo/settings/base.py
scrapgo/settings/utils.py