Metadata-Version: 2.1
Name: scrapgo
Version: 1.5.2
Summary: Convenient crawling framework using as wrapper of reqeusts, requests-cache, beautifulsoup, etc.
Home-page: https://github.com/zwolf21/scrapgo
Author: HS Moon
Author-email: pbr112@naver.com
License: MIT
Keywords: scrapgo,crawling,scrapping,scrap,web
Classifier: Programming Language :: Python :: 3.8
Classifier: Programming Language :: Python :: 3.9
Classifier: Programming Language :: Python :: 3.10
Classifier: Programming Language :: Python :: 3.11
Classifier: Operating System :: OS Independent
Classifier: Topic :: Communications :: Email
Requires-Python: >=3.8
